setup.py
tornado_tools/__init__.py
tornado_tools/decorators.py
tornado_tools/handlers.py
tornado_tools/session.py
tornado_tools/tpl_funcs.py
tornado_tools.egg-info/PKG-INFO
tornado_tools.egg-info/SOURCES.txt
tornado_tools.egg-info/dependency_links.txt
tornado_tools.egg-info/top_level.txt